actstream/__init__.py
actstream/actions.py
actstream/admin.py
actstream/apps.py
actstream/compat.py
actstream/decorators.py
actstream/feeds.py
actstream/gfk.py
actstream/jsonfield.py
actstream/managers.py
actstream/models.py
actstream/registry.py
actstream/settings.py
actstream/signals.py
actstream/urls.py
actstream/views.py
actstream/locale/en/LC_MESSAGES/django.po
actstream/locale/es/LC_MESSAGES/django.po
actstream/locale/nl/LC_MESSAGES/django.po
actstream/locale/pt_BR/LC_MESSAGES/django.po
actstream/locale/sv/LC_MESSAGES/django.po
actstream/migrations/0001_initial.py
actstream/migrations/0002_remove_action_data.py
actstream/migrations/0003_add_follow_flag.py
actstream/migrations/__init__.py
actstream/templates/actstream/action.html
actstream/templates/actstream/actor.html
actstream/templates/actstream/base.html
actstream/templates/actstream/detail.html
actstream/templates/actstream/followers.html
actstream/templates/actstream/following.html
actstream/templatetags/__init__.py
actstream/templatetags/activity_tags.py
actstream/tests/__init__.py
actstream/tests/base.py
actstream/tests/test_activity.py
actstream/tests/test_apps.py
actstream/tests/test_feeds.py
actstream/tests/test_gfk.py
actstream/tests/test_views.py
actstream/tests/test_zombies.py
picsellia_activity_stream-0.9.0.dist-info/AUTHORS.txt
picsellia_activity_stream-0.9.0.dist-info/LICENSE.txt
picsellia_activity_stream-0.9.0.dist-info/METADATA
picsellia_activity_stream-0.9.0.dist-info/WHEEL
picsellia_activity_stream-0.9.0.dist-info/top_level.txt
picsellia_activity_stream-0.9.0.dist-info/RECORD
