Metadata-Version: 2.1
Name: picsellia-activity-stream
Version: 0.9.0
Summary: Generate generic activity streams from the actions on your site. Users can follow any actors' activities for personalized streams.
Home-page: http://github.com/justquick/django-activity-stream
Author: Pierre-Nicolas Tiffreau
Author-email: pierre-nicolas@picsellia.com
License: BSD 3-Clause
Platform: UNKNOWN
Classifier: Development Status :: 5 - Production/Stable
Classifier: Environment :: Web Environment
Classifier: Framework :: Django
Classifier: Intended Audience :: Developers
Classifier: License :: OSI Approved :: BSD License
Classifier: Operating System :: OS Independent
Classifier: Programming Language :: Python
Classifier: Programming Language :: Python :: 3
Classifier: Topic :: Utilities
